{
	"artifacts" : 
	[
		{
			"path" : "llama/common/CMakeFiles/build_info.dir/./build-info.cpp.o"
		}
	],
	"backtrace" : 1,
	"backtraceGraph" : 
	{
		"commands" : 
		[
			"add_library",
			"add_compile_options",
			"llama_add_compile_flags"
		],
		"files" : 
		[
			"/root/.hermes/projects/moreader-android/llama.cpp/common/CMakeLists.txt",
			"/root/.hermes/projects/moreader-android/llama.cpp/cmake/common.cmake"
		],
		"nodes" : 
		[
			{
				"file" : 0
			},
			{
				"command" : 0,
				"file" : 0,
				"line" : 48,
				"parent" : 0
			},
			{
				"command" : 2,
				"file" : 0,
				"line" : 5,
				"parent" : 0
			},
			{
				"command" : 1,
				"file" : 1,
				"line" : 27,
				"parent" : 2
			}
		]
	},
	"compileGroups" : 
	[
		{
			"compileCommandFragments" : 
			[
				{
					"fragment" : "-g -DANDROID -fdata-sections -ffunction-sections -funwind-tables -fstack-protector-strong -no-canonical-prefixes -D_FORTIFY_SOURCE=2 -Wformat -Werror=format-security   -fno-limit-debug-info  -fPIC"
				},
				{
					"backtrace" : 3,
					"fragment" : "-Wmissing-declarations"
				},
				{
					"backtrace" : 3,
					"fragment" : "-Wmissing-noreturn"
				},
				{
					"backtrace" : 3,
					"fragment" : "-Wall"
				},
				{
					"backtrace" : 3,
					"fragment" : "-Wextra"
				},
				{
					"backtrace" : 3,
					"fragment" : "-Wpedantic"
				},
				{
					"backtrace" : 3,
					"fragment" : "-Wcast-qual"
				},
				{
					"backtrace" : 3,
					"fragment" : "-Wno-unused-function"
				},
				{
					"backtrace" : 3,
					"fragment" : "-Wunreachable-code-break"
				},
				{
					"backtrace" : 3,
					"fragment" : "-Wunreachable-code-return"
				},
				{
					"backtrace" : 3,
					"fragment" : "-Wmissing-prototypes"
				},
				{
					"backtrace" : 3,
					"fragment" : "-Wextra-semi"
				}
			],
			"language" : "CXX",
			"sourceIndexes" : 
			[
				0
			],
			"sysroot" : 
			{
				"path" : "/opt/android-sdk/ndk/27.0.12077973/toolchains/llvm/prebuilt/linux-x86_64/sysroot"
			}
		}
	],
	"id" : "build_info::@aad2977ebe3030e60789",
	"name" : "build_info",
	"paths" : 
	{
		"build" : "llama/common",
		"source" : "/root/.hermes/projects/moreader-android/llama.cpp/common"
	},
	"sourceGroups" : 
	[
		{
			"name" : "Source Files",
			"sourceIndexes" : 
			[
				0
			]
		},
		{
			"name" : "CMake Rules",
			"sourceIndexes" : 
			[
				1
			]
		}
	],
	"sources" : 
	[
		{
			"backtrace" : 1,
			"compileGroupIndex" : 0,
			"isGenerated" : true,
			"path" : "/root/.hermes/projects/moreader-android/llama.cpp/common/build-info.cpp",
			"sourceGroupIndex" : 0
		},
		{
			"backtrace" : 0,
			"isGenerated" : true,
			"path" : "/root/.hermes/projects/moreader-android/llama.cpp/common/build-info.cpp.rule",
			"sourceGroupIndex" : 1
		}
	],
	"type" : "OBJECT_LIBRARY"
}
